skyscanner/__init__.py
skyscanner/skyscanner.py
skyscanner-1.1.4.dist-info/DESCRIPTION.rst
skyscanner-1.1.4.dist-info/METADATA
skyscanner-1.1.4.dist-info/RECORD
skyscanner-1.1.4.dist-info/WHEEL
skyscanner-1.1.4.dist-info/metadata.json
skyscanner-1.1.4.dist-info/pbr.json
skyscanner-1.1.4.dist-info/top_level.txt
