Metadata-Version: 2.0
Name: skyscanner
Version: 1.1.4
Summary: Skyscanner Python SDK
Home-page: https://github.com/Skyscanner/skyscanner-python-sdk
Author: Ardy Dedase
Author-email: ardy.dedase@skyscanner.net
License: Apache
Keywords: skyscanner travel api business sdk flights hotels
Platform: UNKNOWN
Classifier: Development Status :: 5 - Production/Stable
Classifier: Intended Audience :: Developers
Classifier: License :: OSI Approved :: Apache Software License
Classifier: Natural Language :: English
Classifier: Programming Language :: Python :: 2
Classifier: Programming Language :: Python :: 2.6
Classifier: Programming Language :: Python :: 2.7
Classifier: Programming Language :: Python :: 3
Classifier: Programming Language :: Python :: 3.3
Classifier: Programming Language :: Python :: 3.4
Requires-Dist: requests
Provides-Extra: Faster XML processing
Requires-Dist: lxml; extra == 'Faster XML processing'
